xPOURY4_recon/__init__.py
xPOURY4_recon/main.py
xPOURY4_recon/core/__init__.py
xPOURY4_recon/core/config_manager.py
xPOURY4_recon/core/exceptions.py
xPOURY4_recon/core/logger.py
xPOURY4_recon/core/recon_engine.py
xPOURY4_recon/modules/__init__.py
xPOURY4_recon/modules/base_module.py
xPOURY4_recon/modules/domain_recon.py
xPOURY4_recon/modules/github_recon.py
xPOURY4_recon/modules/linkedin_recon.py
xPOURY4_recon/modules/phone_recon.py
xPOURY4_recon/modules/shodan_recon.py
xPOURY4_recon/web/__init__.py
xPOURY4_recon/web/app.py
xPOURY4_recon/web/templates/base.html
xPOURY4_recon/web/templates/comprehensive_recon.html
xPOURY4_recon/web/templates/domain_recon.html
xPOURY4_recon/web/templates/error.html
xPOURY4_recon/web/templates/github_recon.html
xPOURY4_recon/web/templates/index.html
xPOURY4_recon/web/templates/linkedin_recon.html
xPOURY4_recon/web/templates/phone_recon.html
xPOURY4_recon/web/templates/results.html
xPOURY4_recon/web/templates/settings.html
xPOURY4_recon/web/templates/shodan_recon.html
xpoury4_recon-1.0.1.data/data/LICENSE
xpoury4_recon-1.0.1.data/data/README.md
xpoury4_recon-1.0.1.data/data/config.yaml
xpoury4_recon-1.0.1.data/data/requirements.txt
xpoury4_recon-1.0.1.dist-info/licenses/LICENSE
xpoury4_recon-1.0.1.dist-info/METADATA
xpoury4_recon-1.0.1.dist-info/WHEEL
xpoury4_recon-1.0.1.dist-info/entry_points.txt
xpoury4_recon-1.0.1.dist-info/top_level.txt
xpoury4_recon-1.0.1.dist-info/RECORD
