Metadata-Version: 2.4
Name: xPOURY4-recon
Version: 1.0.1
Summary: Elite Cyber Intelligence & Digital Forensics Platform - Next-generation OSINT framework
Home-page: https://github.com/xPOURY4/xPOURY4-recon
Download-URL: https://github.com/xPOURY4/xPOURY4-recon/archive/v1.0.1.tar.gz
Author: xPOURY4
Author-email: xPOURY4 <xpoury4@proton.me>
Maintainer: xPOURY4
Maintainer-email: xPOURY4 <xpoury4@proton.me>
License: MIT
Project-URL: Homepage, https://github.com/xPOURY4/xPOURY4-recon
Project-URL: Documentation, https://github.com/xPOURY4/xPOURY4-recon#readme
Project-URL: Repository, https://github.com/xPOURY4/xPOURY4-recon
Project-URL: Bug Reports, https://github.com/xPOURY4/xPOURY4-recon/issues
Project-URL: Changelog, https://github.com/xPOURY4/xPOURY4-recon/releases
Project-URL: Source Code, https://github.com/xPOURY4/xPOURY4-recon
Keywords: osint,reconnaissance,cybersecurity,intelligence,forensics,github,domain,phone,linkedin,shodan,security,penetration-testing,ethical-hacking,digital-forensics,threat-intelligence,information-gathering,recon,investigation
Platform: any
Classifier: Development Status :: 4 - Beta
Classifier: Intended Audience :: Information Technology
Classifier: Intended Audience :: System Administrators
Classifier: Intended Audience :: Developers
Classifier: Intended Audience :: Education
Classifier: Topic :: Security
Classifier: Topic :: Internet :: WWW/HTTP :: Indexing/Search
Classifier: Topic :: System :: Networking :: Monitoring
Classifier: Topic :: Software Development :: Libraries :: Python Modules
Classifier: Topic :: Scientific/Engineering :: Information Analysis
Classifier: License :: OSI Approved :: MIT License
Classifier: Operating System :: OS Independent
Classifier: Operating System :: POSIX :: Linux
Classifier: Operating System :: Microsoft :: Windows
Classifier: Operating System :: MacOS
Classifier: Programming Language :: Python :: 3
Classifier: Programming Language :: Python :: 3.8
Classifier: Programming Language :: Python :: 3.9
Classifier: Programming Language :: Python :: 3.10
Classifier: Programming Language :: Python :: 3.11
Classifier: Programming Language :: Python :: 3.12
Classifier: Programming Language :: Python :: 3.13
Classifier: Programming Language :: Python :: 3 :: Only
Classifier: Environment :: Console
Classifier: Environment :: Web Environment
Classifier: Natural Language :: English
Requires-Python: >=3.8
License-File: LICENSE
Requires-Dist: requests>=2.31.0
Requires-Dist: aiohttp>=3.8.0
Requires-Dist: asyncio>=3.4.3
Requires-Dist: pyyaml>=6.0
Requires-Dist: colorama>=0.4.6
Requires-Dist: rich>=13.0.0
Requires-Dist: click>=8.1.0
Requires-Dist: python-dotenv>=1.0.0
Requires-Dist: dnspython>=2.4.0
Requires-Dist: phonenumbers>=8.13.0
Requires-Dist: whois>=0.9.27
Requires-Dist: shodan>=1.30.0
Requires-Dist: python-whois>=0.8.0
Requires-Dist: certifi>=2023.7.22
Requires-Dist: urllib3>=2.0.0
Requires-Dist: charset-normalizer>=3.2.0
Requires-Dist: idna>=3.4
Requires-Dist: tqdm>=4.66.0
Requires-Dist: tabulate>=0.9.0
Requires-Dist: validators>=0.22.0
Requires-Dist: user-agents>=2.2.0
Requires-Dist: fake-useragent>=1.4.0
Requires-Dist: lxml>=4.9.0
Requires-Dist: beautifulsoup4>=4.12.0
Requires-Dist: selenium>=4.15.0
Requires-Dist: webdriver-manager>=4.0.0
Requires-Dist: python-dateutil>=2.8.0
Requires-Dist: pytz>=2023.3
Requires-Dist: flask>=2.3.0
Requires-Dist: flask-socketio>=5.3.0
Provides-Extra: dev
Requires-Dist: pytest>=7.0.0; extra == "dev"
Requires-Dist: pytest-cov>=4.0.0; extra == "dev"
Requires-Dist: black>=22.0.0; extra == "dev"
Requires-Dist: flake8>=5.0.0; extra == "dev"
Requires-Dist: mypy>=1.0.0; extra == "dev"
Requires-Dist: pre-commit>=2.20.0; extra == "dev"
Provides-Extra: web
Requires-Dist: flask>=2.3.0; extra == "web"
Requires-Dist: flask-socketio>=5.3.0; extra == "web"
Requires-Dist: gunicorn>=21.0.0; extra == "web"
Provides-Extra: all
Requires-Dist: pytest>=7.0.0; extra == "all"
Requires-Dist: pytest-cov>=4.0.0; extra == "all"
Requires-Dist: black>=22.0.0; extra == "all"
Requires-Dist: flake8>=5.0.0; extra == "all"
Requires-Dist: mypy>=1.0.0; extra == "all"
Requires-Dist: pre-commit>=2.20.0; extra == "all"
Requires-Dist: flask>=2.3.0; extra == "all"
Requires-Dist: flask-socketio>=5.3.0; extra == "all"
Requires-Dist: gunicorn>=21.0.0; extra == "all"
Dynamic: author
Dynamic: download-url
Dynamic: home-page
Dynamic: license-file
Dynamic: maintainer
Dynamic: platform
Dynamic: requires-python
